hilbertcurve/__init__.py
hilbertcurve/hilbertcurve.py
hilbertcurve-2.0.5.dist-info/LICENSE
hilbertcurve-2.0.5.dist-info/METADATA
hilbertcurve-2.0.5.dist-info/WHEEL
hilbertcurve-2.0.5.dist-info/top_level.txt
hilbertcurve-2.0.5.dist-info/RECORD
