Metadata-Version: 2.1
Name: hilbertcurve
Version: 2.0.5
Summary: Construct Hilbert Curves.
Home-page: https://github.com/galtay/hilbertcurve
Author: Gabriel Altay
Author-email: gabriel.altay@gmail.com
License: MIT
Keywords: fractal space-filling-curves hilbert hilbert-curve python python3
Platform: UNKNOWN
Classifier: Intended Audience :: Developers
Classifier: License :: OSI Approved :: MIT License
Classifier: Programming Language :: Python :: 3 :: Only
Requires-Python: >=3.6
Provides-Extra: dev
